deepchopper/__init__.py
deepchopper/__init__.pyi
deepchopper/__main__.py
deepchopper/cli.py
deepchopper/data/__init__.py
deepchopper/data/components/__init__.py
deepchopper/data/encode_fq.py
deepchopper/data/fq_datamodule.py
deepchopper/data/hg_data.py
deepchopper/data/only_fq.py
deepchopper/deepchopper.abi3.so
deepchopper/eval.py
deepchopper/models/__init__.py
deepchopper/models/basic_module.py
deepchopper/models/callbacks.py
deepchopper/models/cnn.py
deepchopper/models/components/__init__.py
deepchopper/models/dc_hg.py
deepchopper/models/llm/__init__.py
deepchopper/models/llm/caduceus.py
deepchopper/models/llm/components.py
deepchopper/models/llm/head.py
deepchopper/models/llm/hyena.py
deepchopper/models/llm/metric.py
deepchopper/models/llm/tokenizer.py
deepchopper/models/transformer.py
deepchopper/py.typed
deepchopper/train.py
deepchopper/ui/__init__.py
deepchopper/ui/main.py
deepchopper/utils/__init__.py
deepchopper/utils/instantiators.py
deepchopper/utils/logging_utils.py
deepchopper/utils/preprocess.py
deepchopper/utils/print.py
deepchopper/utils/pylogger.py
deepchopper/utils/rich_utils.py
deepchopper/utils/utils.py
deepchopper-1.3.1.dist-info/METADATA
deepchopper-1.3.1.dist-info/WHEEL
deepchopper-1.3.1.dist-info/entry_points.txt
deepchopper-1.3.1.dist-info/licenses/LICENSE
deepchopper-1.3.1.dist-info/RECORD
