Metadata-Version: 2.4
Name: deepchopper
Version: 1.3.1
Classifier: Development Status :: 5 - Production/Stable
Classifier: Environment :: Console
Classifier: Intended Audience :: Science/Research
Classifier: License :: OSI Approved :: Apache Software License
Classifier: Operating System :: OS Independent
Classifier: Programming Language :: Python
Classifier: Programming Language :: Python :: 3
Classifier: Programming Language :: Python :: 3 :: Only
Classifier: Programming Language :: Python :: 3.10
Classifier: Programming Language :: Python :: 3.11
Classifier: Programming Language :: Python :: 3.12
Classifier: Programming Language :: Rust
Classifier: Topic :: Scientific/Engineering
Requires-Dist: torch>=2.6.0
Requires-Dist: lightning>=2.1.2
Requires-Dist: torchmetrics>=1.2.1
Requires-Dist: rich>=13.7.0
Requires-Dist: transformers>=4.37.2
Requires-Dist: safetensors>=0.4.2
Requires-Dist: datasets>=3.0.0
Requires-Dist: evaluate>=0.4.3
Requires-Dist: typer>=0.12.0
Requires-Dist: gradio==5.0.1
Requires-Dist: fastapi==0.112.2
Requires-Dist: scikit-learn>=1.5.2
Requires-Dist: hydra-core>=1.3.2
Requires-Dist: omegaconf>=2.3.0
Requires-Dist: pyfastx>=2.2.0
Requires-Dist: deepchopper-cli>=1.3.1
License-File: LICENSE
Summary: Genomic language model mitigates chimera artifacts in nanopore direct RNA sequencing
Keywords: deep learning,bioinformatics,rust
Home-Page: https://serde.rs
Author-email: Yangyang Li <<yangyang.li@northwestern.edu>>, Ting-you Wang <<tywang@northwestern.edu>>
Requires-Python: >=3.10
Project-URL: changelog, https://github.com/ylab-hi/DeepChopper/README.md
Project-URL: documentation, https://github.com/ylab-hi/DeepChopper
Project-URL: homepage, https://github.com/ylab-hi/DeepChopper
Project-URL: repository, https://github.com/ylab-hi/DeepChopper
